{"status": "active", "title_thumb_img": "https://static.wanted.co.kr/images/company/30250/utdxotyouiffwjaw__400_400.jpg", "is_newbie": false, "currency": "KRW", "logo_thumb_img": "https://static.wanted.co.kr/images/wdes/0_5.4f43a674.png", "logo_img": "https://static.wanted.co.kr/images/wdes/0_4.4f43a674.png", "address": {"country": "\ud55c\uad6d", "id": 35948, "location": "\uc11c\uc6b8"}, "confirm_time": "2022-08-24T16:39:54", "id": 104127, "category": "IT", "main_tasks": "\uc8fc\uc694 \uc5c5\ubb34\n   \u2022 \uc628\ub77c\uc778 \uc6f9 \uc11c\ube44\uc2a4 \uac1c\ubc1c\n   \u2022 \uc5c5\ubb34\uc2dc\uc2a4\ud15c \uac1c\ubc1c\n\n\ud544\uc218\uc9c0\uc6d0\uc11c\ub958\n   \u2022 \uacbd\ub825\uae30\uc220\uc11c(\ud3ec\ud2b8\ud3f4\ub9ac\uc624)\n\n\ucc44\uc6a9\uc808\ucc28\n   \u2022 \uc11c\ub958 \uc804\ud615 \uff1e \uc2e4\ubb34\uc9c4 \uba74\uc811 \uff1e \uacbd\uc601\uc9c4 \uba74\uc811", "requirements": "\u2022 \ud504\ub860\ud2b8\uc5d4\ub4dc \uc6f9\uac1c\ubc1c, JAVA/JSP, \ud45c\uc900\ud504\ub808\uc784\uc6cc\ud06c (Spring FrameWork)\n\u2022 MySql\n\u2022 Python, VBA", "job_country": "KR", "industry": "IT, \ucee8\ud150\uce20", "company_id": 30250, "title_img": "https://static.wanted.co.kr/images/company/30250/utdxotyouiffwjaw__1080_790.jpg", "due_time": "2022-12-31T00:00:00", "location": "\uc11c\uc6b8 \uc911\uad6c \uc0bc\uc77c\ub300\ub85c 343", "is_expert": true, "sub_categories": ["Java Developer", "\uc790\ubc14 \uac1c\ubc1c\uc790", "Front-end Engineer", "\ud504\ub860\ud2b8\uc5d4\ub4dc \uac1c\ubc1c\uc790", "Web Developer", "\uc6f9 \uac1c\ubc1c\uc790"], "position": "JAVA \uc6f9 \uc5b4\ud50c\ub9ac\ucf00\uc774\uc158 \uac1c\ubc1c\uc790", "reward": 1000000, "jd": "\ud55c\uad6d\uc774\uc5d0\uc2a4\uc9c0\uc5f0\uad6c\uc18c\ub294 \ub300\uc2e0\uae08\uc735\uadf8\ub8f9\uc758 \uacc4\uc5f4\uc0ac\ub85c ESG\ud3c9\uac00, ESG\uc804\ub7b5, \ub9ac\uc11c\uce58 \ubc0f \ucc45\uc784\ud22c\uc790\uc640 \uad00\ub828\ub41c \uc5f0\uad6c\uc5d0 \ud2b9\ud654\ub41c \uc5f0\uad6c\uae30\uad00 \uc785\ub2c8\ub2e4.\n\n\uad6d\ubbfc\uc5f0\uae08 \ub4f1 \uae30\uad00\ud22c\uc790\uc790\uc758 \ucc45\uc784\ud22c\uc790 \ud655\ub300\uc640 ESG\uad00\ub828 \uc81c\ub3c4 \uc815\ube44 \ub4f1\uc73c\ub85c ESG \ud3c9\uac00 \ubc0f \ub9ac\uc11c\uce58, \ucc45\uc784\ud22c\uc790\uc5d0 \ub300\ud55c \uc911\uc694\uc131\uc740 \ub098\ub0a0\ud788 \ud655\ub300\ub418\uace0 \uc788\uc2b5\ub2c8\ub2e4.\n\n\uad00\ub828 \uc5f0\uad6c\ub97c \uc9c4\ud589 \ud558\uae30\uc704\ud574 \ub2e4\uc591\ud55c \ub370\uc774\ud130 \ucc98\ub9ac \ubc0f \ud3c9\uac00\ub97c \uc704\ud55c \uc5c5\ubb34 \uc2dc\uc2a4\ud15c\uc744 \ub514\uc9c0\ud138\ud601\uc2e0\ubcf8\ubd80\uc5d0\uc11c \uad6c\ucd95 \ud558\uace0 \uc788\uc73c\uba70 \ud568\uae68 \ub9cc\ub4e4\uc5b4 \ub098\uac08 \uac1c\ubc1c\uc790\ub97c \ucda9\uc6d0 \ud558\ub824 \ud569\ub2c8\ub2e4.\n\n\n\uc8fc\uc694\uc5c5\ubb34\n\uc8fc\uc694 \uc5c5\ubb34\n   \u2022 \uc628\ub77c\uc778 \uc6f9 \uc11c\ube44\uc2a4 \uac1c\ubc1c\n   \u2022 \uc5c5\ubb34\uc2dc\uc2a4\ud15c \uac1c\ubc1c\n\n\ud544\uc218\uc9c0\uc6d0\uc11c\ub958\n   \u2022 \uacbd\ub825\uae30\uc220\uc11c(\ud3ec\ud2b8\ud3f4\ub9ac\uc624)\n\n\ucc44\uc6a9\uc808\ucc28\n   \u2022 \uc11c\ub958 \uc804\ud615 \uff1e \uc2e4\ubb34\uc9c4 \uba74\uc811 \uff1e \uacbd\uc601\uc9c4 \uba74\uc811\n\n\uc790\uaca9\uc694\uac74\n\u2022 \ud504\ub860\ud2b8\uc5d4\ub4dc \uc6f9\uac1c\ubc1c, JAVA/JSP, \ud45c\uc900\ud504\ub808\uc784\uc6cc\ud06c (Spring FrameWork)\n\u2022 MySql\n\u2022 Python, VBA\n\n\uc6b0\ub300\uc0ac\ud56d\n\u2022 \ud504\ub860\ud2b8\uc5d4\ub4dc \uac1c\ubc1c\n\u2022 \uc2a4\ud0c0\ud2b8\uc5c5 \uacbd\ud5d8\uc790(\ubd84\uc57c \ubb34\uad00)\n\u2022 \uc2dc\uc2a4\ud15c \uc124\uacc4, \uae30\ud68d \uacbd\ub825\n\n\ud61c\ud0dd \ubc0f \ubcf5\uc9c0\n\u2022 \ub3c4\uc11c\uad6c\ub9e4, \uc720\ub8cc\uac15\uc758 \ub4f1 \uc790\uae30\uac1c\ubc1c \uc9c0\uc6d0\n\u2022 \uac74\uac15\uac80\uc9c4, \uacbd\uc870\uc0ac, \uc790\uc720\ub85c\uc6b4 \uc5f0\ucc28 \ubd84\ud560 \uc0ac\uc6a9, \uccb4\ub825\ub2e8\ub828 \ud734\uac00 \ub4f1 \n  \uff1e\uff1e \uc0dd\uac01\ud558\ub294 \ub300\ubd80\ubd84\uc758 \ubcf5\uc9c0\n\u2022 \uae30\ud0c0. \ub300\uc2e0\ud30c\uc774\ub0b8\uc2a4\uc13c\ud130 \ucf8c\uc801\ud55c \uc0ac\ubb34\uacf5\uac04, \uba85\ub3d9\uc131\ub2f9 \ubdf0\n\n", "company_name": "\ud55c\uad6d\uc774\uc5d0\uc2a4\uc9c0\uc5f0\uad6c\uc18c", "lang": "ko", "gps_x": "126.986959615068", "gps_y": "37.5651004556362"}