{"status": "active", "title_thumb_img": "https://static.wanted.co.kr/images/company/31184/zwns5hw6wxwo7ybr__400_400.jpg", "is_newbie": false, "currency": "KRW", "logo_thumb_img": "https://static.wanted.co.kr/images/wdes/0_5.c002847f.jpg", "logo_img": "https://static.wanted.co.kr/images/wdes/0_4.c002847f.jpg", "address": {"country": "\ud55c\uad6d", "id": 46329, "location": "\uc11c\uc6b8"}, "confirm_time": "2022-11-08T10:27:23", "id": 120365, "category": "IT", "main_tasks": "- \ube44\uc0ac\uc774\ub4dc \uc8fc\uc8fc \ud50c\ub7ab\ud3fc\uc758 \ud504\ub860\ud2b8\uc5d4\ub4dc \uac1c\ubc1c\n- \ubc31\uc5d4\ub4dc \uac1c\ubc1c\uc790\uc640 \uc81c\ud488 \ub514\uc790\uc774\ub108\uc640\uc758 \ud611\uc5c5\uc744 \ud1b5\ud55c \ud504\ub860\ud2b8\uc5d4\ub4dc \uc124\uacc4 \ubc0f \uc791\uc5c5\n- \uac1c\ubc1c\uc870\uc9c1 \ub0b4 \ucf54\ub4dc\ub9ac\ubdf0 \ubc0f \uc2dc\uc2a4\ud15c \ub514\uc790\uc778\uc5d0 \uad00\ud55c \uc758\uc0ac\uacb0\uc815\uc744 \ud568\uaed8 \ud558\uac8c \ub429\ub2c8\ub2e4.", "requirements": "- Front-end: Redwoodjs + Storybook + GraphQL + TailwindCSS\n- App: Flutter + Fastlane\n- Back-end: Redwoodjs + serverless + AWS Lambda\n- \ub370\uc774\ud130\ubca0\uc774\uc2a4: PostgreSQL + Amazon RDS\n- \uc0ac\ub0b4 \uc2dc\uc2a4\ud15c: python + fastAPI", "job_country": "KR", "industry": "IT, \ucee8\ud150\uce20", "company_id": 31184, "title_img": "https://static.wanted.co.kr/images/company/31184/zwns5hw6wxwo7ybr__1080_790.jpg", "due_time": "2022-11-30T00:00:00", "location": "\uacf5\ub355 \uc11c\uc6b8\ucc3d\uc5c5\ud5c8\ube0c \ubcc4\uad00", "is_expert": true, "sub_categories": ["Front-end Engineer", "\ud504\ub860\ud2b8\uc5d4\ub4dc \uac1c\ubc1c\uc790"], "position": "Front-end \uac1c\ubc1c\uc790", "reward": 1000000, "jd": "\"\ud68c\uc0ac\uc758 \ub9e4\ucd9c\uc740 \uc624\ub974\ub294\ub370 \uc65c \ub0b4 \uc8fc\uc2dd\uc740 \uadf8\ub300\ub85c\uc778\uac00\uc694?\"\n\n\ud55c\uad6d \uacbd\uc81c\ub294 \ud56d\uc0c1 '\ucf54\ub9ac\uc544 \ub514\uc2a4\uce74\uc6b4\ud2b8'\ub77c\ub294 \uc800\ud3c9\uac00\uc758 \ub2aa\uc5d0 \ube60\uc838 \uc788\ub2e4. \uc81c\uc77c \ud070 \uc694\uc778\uc740 ESG\uc911 G\uc5d0 \ud574\ub2f9\ud558\ub294 \ud55c\uad6d\uc758 \uae30\uc5c5\uc9c0\ubc30\uad6c\uc870\uc640 \uacbd\uc601 \ud22c\uba85\uc131 \ubd80\ubb38\uc774\ub2e4. \ud55c\uad6d \uae30\uc5c5\uc740 \uc18c\uc218 \ub300\uc8fc\uc8fc\uc758 \uc774\uc775 \uc704\uc8fc\ub85c \ud68c\uc0ac\uac00 \uc6b4\uc601\ub418\ub294 \uacbd\uc6b0\uac00 \ub9ce\uc73c\uba70, \uae30\uc5c5\uc740 \uc8fc\uc8fc\ub4e4\uc758 \uc18c\uc720\ub77c\ub294 \uc790\ubcf8\uc8fc\uc758\uc801 \uc778\uc2dd\uc774 \ubd80\uc871\ud558\ub2e4. \uc218\uc775\uc131\uacfc \uc790\uc0b0\uac00\uce58\uac00 \ud574\uc678 \uae30\uc5c5\uacfc \ube44\uad50\ud588\uc744 \ub54c \ubc00\ub9ac\uc9c0 \uc54a\ub294 \uc218\uc900\uc774\ub77c \ud558\ub354\ub77c\ub3c4 \ucf54\ub9ac\uc544 \ub514\uc2a4\uce74\uc6b4\ud2b8\uac00 \uc801\uc6a9\ub418\uba74 \ucd5c\ub300 6~70% \ud3c9\uac00 \uc808\ud558\ub41c\ub2e4.\n\n\ube44\uc0ac\uc774\ub4dc\ucf54\ub9ac\uc544\ub294 \uc8fc\uc8fc\uc640 \ud568\uaed8 \uac70\ubc84\ub10c\uc2a4\ub97c \uac1c\uc120\ud558\uace0\uc790 \ud558\ub294 \ucee4\ubba4\ub2c8\ud2f0 \ud50c\ub7ab\ud3fc\uc744 \uad6c\ucd95\ud558\uace0\uc790 \ud569\ub2c8\ub2e4. 22\ub144 3\uc6d4 \uc804\uc790\uc704\uc784 \uae30\ub2a5\uc744 \ucd9c\uc2dc\ud558\uc600\uace0, \ub7f0\uce6d 1\ub2ec\ub9cc\uc5d0 1,200\uc5b5\uc6d0\uc758 \uc8fc\uc2dd\uc744 \uc704\uc784\ubc1b\uc544, \uc5d0\uc2a4\uc5e0 \ucea0\ud398\uc778\uc5d0\uc11c \uc644\uc2b9\uc744 \uac70\ub450\uc5b4 \uad6d\ub0b4 \uc790\ubcf8\uc2dc\uc7a5 \uc5ed\uc0ac\uc0c1 \ucc98\uc74c\uc73c\ub85c \ud589\ub3d9\uc8fc\uc758\ub97c \uc131\uacf5\uc2dc\ud0a8 \ud50c\ub7ab\ud3fc\uc774 \ub418\uc5c8\uc2b5\ub2c8\ub2e4. \uc55e\uc73c\ub85c \ube44\uc0ac\uc774\ub4dc\ucf54\ub9ac\uc544\ub294 \uc99d\uad8c\uc0ac \uc5f0\ub3d9, \uc8fc\uc8fc \uc9d1\uacb0\ub825 \uac15\ud654, \uae30\uad00 \ub9e4\uce6d \uc5f0\uacc4\ub97c \uac15\ud654\ud558\uc5ec \ucf54\ub9ac\uc544 \ub514\uc2a4\uce74\uc6b4\ud2b8\ub97c \ud574\uacb0\ud558\uace0\uc790 \ud569\ub2c8\ub2e4.\n\n\n\uc8fc\uc694\uc5c5\ubb34\n- \ube44\uc0ac\uc774\ub4dc \uc8fc\uc8fc \ud50c\ub7ab\ud3fc\uc758 \ud504\ub860\ud2b8\uc5d4\ub4dc \uac1c\ubc1c\n- \ubc31\uc5d4\ub4dc \uac1c\ubc1c\uc790\uc640 \uc81c\ud488 \ub514\uc790\uc774\ub108\uc640\uc758 \ud611\uc5c5\uc744 \ud1b5\ud55c \ud504\ub860\ud2b8\uc5d4\ub4dc \uc124\uacc4 \ubc0f \uc791\uc5c5\n- \uac1c\ubc1c\uc870\uc9c1 \ub0b4 \ucf54\ub4dc\ub9ac\ubdf0 \ubc0f \uc2dc\uc2a4\ud15c \ub514\uc790\uc778\uc5d0 \uad00\ud55c \uc758\uc0ac\uacb0\uc815\uc744 \ud568\uaed8 \ud558\uac8c \ub429\ub2c8\ub2e4.\n\n\uc790\uaca9\uc694\uac74\n- Front-end: Redwoodjs + Storybook + GraphQL + TailwindCSS\n- App: Flutter + Fastlane\n- Back-end: Redwoodjs + serverless + AWS Lambda\n- \ub370\uc774\ud130\ubca0\uc774\uc2a4: PostgreSQL + Amazon RDS\n- \uc0ac\ub0b4 \uc2dc\uc2a4\ud15c: python + fastAPI\n\n\uc6b0\ub300\uc0ac\ud56d\n- CS \uc804\uacf5\uc790 \ub610\ub294 \uadf8\uc5d0 \uc0c1\uc751\ud558\ub294 \uc54c\uace0\ub9ac\uc998, \ub370\uc774\ud130\uad6c\uc870, OS, \ub370\uc774\ud130\ubca0\uc774\uc2a4 \ub4f1 \uae30\ubcf8\uc801\uc778 \uc804\uc0b0 \uc9c0\uc2dd\uc5d0 \ub300\ud55c \uc774\ud574\ub97c \uac16\ucd94\uc2e0 \ubd84\n- \ubb38\uc81c\ud574\uacb0 \ub2a5\ub825\uacfc \ucee4\ubba4\ub2c8\ucf00\uc774\uc158\uc774 \uc6d0\ud65c\ud558\uc2e0 \ubd84\n- \ud22c\uc790\ud55c \uc8fc\uc2dd\uc774 \ub300\uc8fc\uc8fc\uc758 \ud6a1\ud3ec\ub85c \uc778\ud574 \uc190\uc808\ud55c \uacbd\ud5d8\uc774 \uc788\uc73c\uc2e0 \ubd84\n\n\ud61c\ud0dd \ubc0f \ubcf5\uc9c0\n[\ud658\uacbd]\n\n- Mac, \ucee4\ube0c\ub4dc \ubaa8\ub2c8\ud130, \uc2a4\ud0e0\ub529 \ub370\uc2a4\ud06c \ub4f1 \uc7a5\ube44 \uc9c0\uc6d0\n- \ud68c\uc0ac \uc2a4\ub0b5\ubc14 \ubb34\uc81c\ud55c \uc774\uc6a9 \ubc0f \uc2dd\ub300 \uc9c0\uc6d0\n\n[\ubcf5\uc9c0]\n\n- \ub3c4\uc11c, \uac15\uc758, \ucee8\ud37c\ub7f0\uc2a4 \ucc38\uc5ec, \ucee4\ub9ac\uc5b4 \ud328\uc2a4 \uc124\uacc4 \ub4f1 \uac1c\ubc1c\uc790\uc5d0\uac8c \ud544\uc694\ud55c \ubaa8\ub4e0 \uc131\uc7a5 \uc804\ud3ed \uc9c0\uc6d0\n- \ub109\ub109\ud55c \uc810\uc2ec\uc2dc\uac04\n- \uc624\ud6c4 10\uc2dc \uc774\ud6c4 \ud0dd\uc2dc\ube44 \uc9c0\uc6d0\n\n", "company_name": "\ube44\uc0ac\uc774\ub4dc\ucf54\ub9ac\uc544", "lang": "ko"}