{"status": "active", "title_thumb_img": "https://static.wanted.co.kr/images/company/33777/geyu2tllepvudntr__400_400.jpg", "is_newbie": false, "currency": "KRW", "logo_thumb_img": "https://static.wanted.co.kr/images/wdes/0_5.70c4119c.jpg", "logo_img": "https://static.wanted.co.kr/images/wdes/0_4.70c4119c.jpg", "address": {"country": "\ud55c\uad6d", "id": 41193, "location": "\uacbd\uae30"}, "confirm_time": "2022-09-23T18:28:12", "id": 129476, "category": "IT", "main_tasks": "\u2022 System Software (\ud38c\uc6e8\uc5b4) \uac1c\ubc1c\n\u2022 Linux / Android OS \ubc0f \ub514\ubc14\uc774\uc2a4 \ub4dc\ub77c\uc774\ubc84 \uac1c\ubc1c\n\u2022 5G \ubaa8\ub4c8 \ubc0f TCU \uac1c\ubc1c \uc5c5\ubb34", "requirements": "\u2022 \ub300\uc878\uc774\uc0c1 (\uc815\ubcf4\ud1b5\uc2e0,\uc804\uc0b0,\uc804\uc790,\uc804\uae30,\ucef4\ud4e8\ud130\uacf5\ud559 \ub4f1 \uacf5\ud559\uacc4\uc5f4 \uc6b0\ub300)\n\u2022 inux \ubc0f Android OS \ubc0f \ub514\ubc14\uc774\uc2a4 \ub4dc\ub77c\uc774\ubc84 \uac1c\ubc1c \uacbd\ud5d8\uac00\ub2a5\uc790", "job_country": "KR", "industry": "\uc81c\uc870", "company_id": 33777, "title_img": "https://static.wanted.co.kr/images/company/33777/geyu2tllepvudntr__1080_790.jpg", "due_time": null, "location": "\uacbd\uae30\ub3c4 \uc131\ub0a8\uc2dc \ubd84\ub2f9\uad6c \uc7a5\ubbf8\ub85c 42 6\uce35", "is_expert": true, "sub_categories": ["Android Developer", "\uc548\ub4dc\ub85c\uc774\ub4dc \uac1c\ubc1c\uc790", "Video, Voice Engineer", "\uc601\uc0c1,\uc74c\uc131 \uc5d4\uc9c0\ub2c8\uc5b4", "Software Engineer", "Software Engineer", "\uc18c\ud504\ud2b8\uc6e8\uc5b4 \uc5d4\uc9c0\ub2c8\uc5b4"], "position": "SW Firmware \uac1c\ubc1c", "reward": 1000000, "jd": "\uc5d0\uc774\uc5e0\ud154\ub808\ucf64\uc740 20\ub144\uac04 \ud734\ub300\ud3f0-\ud1b5\uc2e0\ubaa8\ub4c8-IoT-Automotive-AI-Cloud \uc81c\ud488\uc744 \uac1c\ubc1c, \ucd9c\uc2dc\ud558\uc5ec \uc2dc\uc7a5\uc744 \uc120\ub3c4\ud574 \uc628 \ud68c\uc0ac \uc785\ub2c8\ub2e4.\n\ucd5c\uace0 \uc218\uc900\uc758 \uae30\uc220\uac1c\ubc1c\uc778\uc7ac\ub4e4\uc774 \ubaa8\uc5ec 5G, \ubbf8\ub798\uc804\uc7a5\uc0ac\uc5c5(TCU\ub4f1), \ucc28\uc138\ub300\ub2e8\ub9d0\uae30\uc758 \uc0c8\ub85c\uc6b4 \uc2dc\ub300\ub97c \uc5f4\uc5b4 \ub098\uac11\ub2c8\ub2e4.\n\ucf54\uc2a4\ub2e5 \uc0c1\uc7a5\uc744 \ubaa9\ud45c\ub85c \ucd94\uc9c4\ud558\uace0 \uc788\uc73c\uba70, 2023\ub144 4\ubd84\uae30 '\uacfc\ucc9c\uc9c0\uc2dd\uc815\ubcf4\ud0c0\uc6b4'\uc5d0 \ubcf8\uc0ac \uc0ac\uc625\uc744 \uc0c8\ub86d\uac8c \ud655\uc7a5\ud560 \uacc4\ud68d\uc785\ub2c8\ub2e4.\n\uc5d0\uc774\uc5e0\ud154\ub808\ucf64\uacfc \ud568\uaed8\ud560 \uc18c\uc911\ud55c \uc778\uc7ac\ub97c \uae30\ub2e4\ub9bd\ub2c8\ub2e4.\n\n\n\uc8fc\uc694\uc5c5\ubb34\n\u2022 System Software (\ud38c\uc6e8\uc5b4) \uac1c\ubc1c\n\u2022 Linux / Android OS \ubc0f \ub514\ubc14\uc774\uc2a4 \ub4dc\ub77c\uc774\ubc84 \uac1c\ubc1c\n\u2022 5G \ubaa8\ub4c8 \ubc0f TCU \uac1c\ubc1c \uc5c5\ubb34\n\n\uc790\uaca9\uc694\uac74\n\u2022 \ub300\uc878\uc774\uc0c1 (\uc815\ubcf4\ud1b5\uc2e0,\uc804\uc0b0,\uc804\uc790,\uc804\uae30,\ucef4\ud4e8\ud130\uacf5\ud559 \ub4f1 \uacf5\ud559\uacc4\uc5f4 \uc6b0\ub300)\n\u2022 inux \ubc0f Android OS \ubc0f \ub514\ubc14\uc774\uc2a4 \ub4dc\ub77c\uc774\ubc84 \uac1c\ubc1c \uacbd\ud5d8\uac00\ub2a5\uc790\n\n\uc6b0\ub300\uc0ac\ud56d\n\u2022 Automotive \uac1c\ubc1c \uacbd\ud5d8\uc790 \uc6b0\ub300\n\u2022 \ud1b5\uc2e0\uc804\uc790\uc81c\ud488 \uac1c\ubc1c \uacbd\ud5d8\uc790 \uc6b0\ub300\n\n\ud61c\ud0dd \ubc0f \ubcf5\uc9c0\n\u2022 \uc720\uc5f0\uadfc\ubb34\uc81c(\uc120\ud0dd\uc801\uadfc\ub85c\uc2dc\uac04\uc81c)\n\u2022 \uc7a5\uae30\uadfc\uc18d\ud3ec\uc0c1\n\u2022 \ucc3d\ub9bd\uae30\ub150\uc77c \ud734\ubb34\n\u2022 \uacbd\uc870\ud734\uac00 \ubc0f \uacbd\uc870\uae08 \uc9c0\uae09\n\u2022 \uc0ac\ub0b4\ub300\ucd9c \uc9c0\uc6d0\n\u2022 \ud1f4\uc9c1\uc5f0\uae08\uc81c\ub3c4\n\u2022 \uc784\uc9c1\uc6d0\ub2e8\uccb4\uc0c1\ud574\ubcf4\ud5d8\n\u2022 \uc120\ud0dd\uc801\ubcf5\ub9ac\ud6c4\uc0dd\uc81c\ub3c4\n\u2022 \ud68c\uc0ac\uc81c\ud734\ucf58\ub3c4 \uc774\uc6a9\n\u2022 \uba85\uc808\uc120\ubb3c\uc9c0\uae09\n\u2022 \uc778\uc13c\ud2f0\ube0c\uc81c\ub3c4\n\n", "company_name": "\uc5d0\uc774\uc5e0\ud154\ub808\ucf64", "lang": "ko", "gps_x": "127.125512004438", "gps_y": "37.4134796425259"}