{"status": "active", "title_thumb_img": "https://static.wanted.co.kr/images/company/18705/ynzm2rxie6dcthot__400_400.jpg", "is_newbie": false, "currency": "KRW", "logo_thumb_img": "https://static.wanted.co.kr/images/wdes/0_5.be8b094a.jpg", "logo_img": "https://static.wanted.co.kr/images/wdes/0_4.be8b094a.jpg", "address": {"country": "\ud55c\uad6d", "id": 20427, "location": "\uc11c\uc6b8"}, "confirm_time": "2022-09-30T14:45:19", "id": 53308, "category": "IT", "main_tasks": "\u00b7 \uba40\ud2f0 / \ud558\uc774\ube0c\ub9ac\ub4dc CMP \uc194\ub8e8\uc158 \uac1c\ubc1c\n\u00b7 VM Cluster, Openstack, OpenShift \uad00\ub9ac API \ucef4\ud3ec\ub10c\ud2b8 \uc124\uacc4/\uac1c\ubc1c/\uc6b4\uc601", "requirements": "\u00b7 \uc911/\uc0c1\uae09 \uc218\uc900\uc758 Java programming\n\u00b7 \ubc31\uc5d4\ub4dc \uac1c\ubc1c \uacbd\ub825 2\ub144 \uc774\uc0c1\n\u00b7 Spring framework\uc744 \ud1b5\ud55c Application \ubc0f RESTful API \uac1c\ubc1c \uacbd\ud5d8\n\u00b7 RDB \ubaa8\ub378\ub9c1/\uac1c\ubc1c/\ud29c\ub2dd(hint/plan) \uc774 \uac00\ub2a5\ud558\uc2e0 \ubd84\n\u00b7 \ub9ac\ub205\uc2a4(CentOS) \uae30\ubc18\uc758 \uc2dc\uc2a4\ud15c \uc0ac\uc6a9 \uacbd\ud5d8\n\u00b7 Git/Git-flow \uc0ac\uc6a9 \uacbd\ud5d8\n\u00b7 \uae30\ubcf8\uc801\uc778 \uc218\uc900\uc758 \uac00\uc0c1\ud654 \uae30\uc220 \uc774\ud574", "job_country": "KR", "industry": "IT, \ucee8\ud150\uce20", "company_id": 18705, "title_img": "https://static.wanted.co.kr/images/company/18705/ynzm2rxie6dcthot__1080_790.jpg", "due_time": null, "location": "\uc11c\uc6b8\uc2dc \uc911\uad6c \uc744\uc9c0\ub85c 100, B\ub3d9 10\uce35 (\ud30c\uc778\uc5d0\ube44\ub274)", "is_expert": true, "sub_categories": ["Java Developer", "\uc790\ubc14 \uac1c\ubc1c\uc790", "Web Developer", "\uc6f9 \uac1c\ubc1c\uc790", "Software Engineer", "Software Engineer", "\uc18c\ud504\ud2b8\uc6e8\uc5b4 \uc5d4\uc9c0\ub2c8\uc5b4"], "position": "CMP \uc194\ub8e8\uc158 \uac1c\ubc1c", "reward": 1000000, "jd": "\uc6b0\ub9ac \uc0ac\ud68c\ub294 \ubcc0\ud654\uc640 \ubb34\ud55c \uacbd\uc7c1 \uc18d\uc5d0\uc11c\ub3c4 \uc9c0\uc18d\uc801\uc778 \ubc1c\uc804\uacfc \uc131\uc7a5\uc73c\ub85c 'IT \ucf54\ub9ac\uc544'\ub97c \uc138\uacc4\uc5d0 \uc54c\ub824\uc654\uc2b5\ub2c8\ub2e4. \ud604\uc7ac \uc6b0\ub9ac\ub294 4\ucc28 \uc0b0\uc5c5\ud601\uba85\uc2dc\ub300\ub97c \ub9de\uc544 \uacfc\uac70\uc640\ub294 \ub2e4\ub978 \ud070 \ubcc0\ud654\uc758 \uc911\uc2ec\uc5d0 \uc11c \uc788\uc2b5\ub2c8\ub2e4. \uc778\uacf5\uc9c0\ub2a5(AI), \uc0ac\ubb3c\uc778\ud130\ub137(IoT), \ube45\ub370\uc774\ud130\u00b7 \ube14\ub85d\uccb4\uc778 \ub4f1\uc758 \uc2e0\uae30\uc220\uacfc \uc18c\ud504\ud2b8\uc6e8\uc5b4 \uac1c\ubc1c \ub2a5\ub825, \ud48d\ubd80\ud55c \uc0ac\uc5c5 \uacbd\ud5d8\uc774 \uacb0\ud569\ud574 4\ucc28 \uc0b0\uc5c5\ud601\uba85\uc758 \uc8fc\ub3c4\uad8c\uc744 \uac00\uc838\uac08 \uc218 \uc788\ub3c4\ub85d \uc900\ube44\ud558\uace0 \uc788\uc2b5\ub2c8\ub2e4. \uad6d\ub0b4\uc678 \uc2dc\uc7a5 \ubcc0\ud654\uc640 \uc5c5\uacc4\uc758 \uc2e0\uc18d\ud55c \ub300\uc751\uc774 \uadf8 \uc5b4\ub290 \ub54c\ubcf4\ub2e4 \uc911\uc694\ud558\uac8c \uc791\uc6a9\ub418\uace0 \uc788\uc2b5\ub2c8\ub2e4. \ub610\ud55c \uae30\uc5c5\uc774 \ubc1c\uc804\ud560\uc218\ub85d \ud63c\uc790\uac00 \uc544\ub2cc \uc5c5\uacc4 \uc804\ubb38 \uae30\uc5c5\ub4e4\uacfc\uc758 \ud568\uaed8 \ud611\uc5c5\uacfc \uc0c1\uc0dd\uc744 \ud1b5\ud574 \uc0ac\uc5c5\uc758 \uae30\ud68c\ub97c \ub9cc\ub4e4\uc5b4 \ub098\uac04\ub2e4\uba74 \uc758\ubbf8\uc640 \ud30c\uae09\ub825\uc740 \ub354 \ud074 \uac83\uc785\ub2c8\ub2e4.\n\n\uc774\ub178\uadf8\ub9ac\ub4dc\ub294 \ub354 \ub9ce\uc740 \uae30\uc5c5\ub4e4\uacfc \ud568\uaed8 \uc131\uc7a5\ud560 \uc218 \uc788\ub3c4\ub85d \uad6d\uc0b0 \ud074\ub77c\uc6b0\ub4dc \uc5d0\ucf54 \uc2dc\uc2a4\ud15c\uc744 \ub9cc\ub4e4\uace0 \ub370\uc774\ud130\uc758 \uc7a0\uc7ac\ub825\uc744 \uc801\uadf9 \ud65c\uc6a9\ud574 4\ucc28 \uc0b0\uc5c5 \ud601\uba85\uc744 \uc8fc\ub3c4\ud574 \ub098\uac00\ub294 \ub3d9\uc2dc\uc5d0 \uad6d\uc0b0 \ud074\ub77c\uc6b0\ub4dc \uae30\uc5c5\uc758\uc0ac\uba85\uac10\uc744 \uac00\uc9c0\uace0 \ub300\ud55c\ubbfc\uad6d ICT\uc0b0\uc5c5 \uc131\uc7a5\uc0ac\uc758 \ubc1c\uc790\ucde8\uc640 \ud568\uaed8 \ud558\uaca0\uc2b5\ub2c8\ub2e4. \uac10\uc0ac\ud569\ub2c8\ub2e4.\n\n\n\uc8fc\uc694\uc5c5\ubb34\n\u00b7 \uba40\ud2f0 / \ud558\uc774\ube0c\ub9ac\ub4dc CMP \uc194\ub8e8\uc158 \uac1c\ubc1c\n\u00b7 VM Cluster, Openstack, OpenShift \uad00\ub9ac API \ucef4\ud3ec\ub10c\ud2b8 \uc124\uacc4/\uac1c\ubc1c/\uc6b4\uc601\n\n\uc790\uaca9\uc694\uac74\n\u00b7 \uc911/\uc0c1\uae09 \uc218\uc900\uc758 Java programming\n\u00b7 \ubc31\uc5d4\ub4dc \uac1c\ubc1c \uacbd\ub825 2\ub144 \uc774\uc0c1\n\u00b7 Spring framework\uc744 \ud1b5\ud55c Application \ubc0f RESTful API \uac1c\ubc1c \uacbd\ud5d8\n\u00b7 RDB \ubaa8\ub378\ub9c1/\uac1c\ubc1c/\ud29c\ub2dd(hint/plan) \uc774 \uac00\ub2a5\ud558\uc2e0 \ubd84\n\u00b7 \ub9ac\ub205\uc2a4(CentOS) \uae30\ubc18\uc758 \uc2dc\uc2a4\ud15c \uc0ac\uc6a9 \uacbd\ud5d8\n\u00b7 Git/Git-flow \uc0ac\uc6a9 \uacbd\ud5d8\n\u00b7 \uae30\ubcf8\uc801\uc778 \uc218\uc900\uc758 \uac00\uc0c1\ud654 \uae30\uc220 \uc774\ud574\n\n\uc6b0\ub300\uc0ac\ud56d\n\u00b7 React, Typescript \uae30\ubc18\uc758 \ud504\ub85c\uc81d\ud2b8 \uacbd\ud5d8\uc774 \uc788\uc73c\uc2e0 \ubd84\n\u00b7 \ubaa8\ub2c8\ud130\ub9c1 \uc218\uc9d1 \ubc0f \ubd84\uc11d \uacbd\ud5d8\uc774 \uc788\uc73c\uc2e0 \ubd84\n\u00b7 \ub9ac\ub205\uc2a4 \ud658\uacbd\uc5d0\uc11c \uac1c\ubc1c \ubc0f \uc6b4\uc601 \uacbd\ud5d8\n\u00b7 \ud37c\ube14\ub9ad \ud074\ub77c\uc6b0\ub4dc(AWS/GCP...)\uc5d0 \ub300\ud55c \ub192\uc740 \uc774\ud574\ub3c4\uac00 \uc788\ub294 \uc5d4\uc9c0\ub2c8\uc5b4\n\u00b7 RabbitMQ \ub4f1 \uba54\uc2dc\uc9d5 \ubbf8\ub4e4\uc6e8\uc5b4\ub97c \uc0ac\uc6a9\ud55c \uac1c\ubc1c \uacbd\ud5d8\n\u00b7 CI/CD \uc6b4\uc601 \uacbd\ud5d8\n\u00b7 K8S \uae30\ubc18 \uac1c\ubc1c \uacbd\ud5d8\n\u00b7 \uc6d0\ub9cc\ud55c \ucee4\ubba4\ub2c8\ucf00\uc774\uc158 \ubc0f \ud611\uc5c5 \ub2a5\ub825\uc744 \uac00\uc9c0\uc2e0 \ubd84\n\u00b7 \uc624\ud508 \uc18c\uc2a4 \ub610\ub294 \uc2e0\uaddc \uae30\uc220 \ud559\uc2b5\uc744 \uc6d0\ud558\uace0 \uc5c5\ubb34\uc5d0 \uc801\uadf9\uc801\uc73c\ub85c \ud65c\uc6a9\ud558\uace0 \uc2f6\uc73c\uc2e0 \ubd84\n\n\ud61c\ud0dd \ubc0f \ubcf5\uc9c0\n. \uc774\ub178\uadf8\ub9ac\ub4dc \ud648\ud398\uc774\uc9c0 \ucc38\uc870\n\n", "company_name": "\uc774\ub178\uadf8\ub9ac\ub4dc", "lang": "ko", "gps_x": "126.988142568678", "gps_y": "37.5656490167105"}