{"status": "active", "title_thumb_img": "https://static.wanted.co.kr/images/company/31582/em6pvsggh1sxqesm__400_400.png", "is_newbie": false, "currency": "KRW", "logo_thumb_img": "https://static.wanted.co.kr/images/wdes/0_5.bd0be0dc.jpg", "logo_img": "https://static.wanted.co.kr/images/wdes/0_4.bd0be0dc.jpg", "address": {"country": "\ud55c\uad6d", "id": 38061, "location": "\uacbd\uae30"}, "confirm_time": "2022-09-22T14:34:34", "id": 109859, "category": "IT", "main_tasks": "\u2022 \uc81c\ud398\ud1a0 \uc2a4\ud06c\ub9bd\ud2b8(TypeScript)\ub97c \ud65c\uc6a9\ud574 \uc81c\ud398\ud1a0 \ub274\uc6d4\ub4dc \uac8c\uc784\uc744 \uac1c\ubc1c\ud569\ub2c8\ub2e4.\n\u2022 \uac1c\ubc1c\uc5d0 \ud544\uc694\ud55c \ub3c4\uad6c\ub97c \uac1c\ubc1c \ubc0f \uc720\uc9c0\ubcf4\uc218\ud569\ub2c8\ub2e4.\n\u2022 \uac1c\ubc1c\ud55c \uc18c\ud504\ud2b8\uc6e8\uc5b4\uc5d0 \ub300\ud55c \ubb38\uc11c\ub97c \uc791\uc131\ud569\ub2c8\ub2e4.", "requirements": "\u2022 1\ub144 \uc774\uc0c1\uc758 \uc720\ub2c8\ud2f0 \uac8c\uc784 \ud074\ub77c\uc774\uc5b8\ud2b8 \uacbd\ub825 \ubc0f \uadf8\uc5d0 \uc900\ud558\ub294 \uacbd\ud5d8\uc774 \uc788\uc73c\uc2e0 \ubd84\uc774 \ud544\uc694\ud569\ub2c8\ub2e4.\n\u2022 \uc720\ub2c8\ud2f0 \uc5d4\uc9c4\uc5d0 \ub300\ud55c \ub192\uc740 \uc774\ud574\ub3c4 \ubc0f \uc0ac\uc6a9 \uacbd\ud5d8\uc774 \uc788\uc73c\uc2e0 \ubd84\uc774 \ud544\uc694\ud569\ub2c8\ub2e4.\n\u2022 \uc608\uc0c1\uce58 \ubabb\ud55c \ub2e4\uc591\ud55c \ubb38\uc81c \uc0c1\ud669\uc5d0 \uc720\uc5f0\ud558\uac8c \ub300\ucc98 \uac00\ub2a5\ud558\uc2e0 \ubd84\uc774 \ud544\uc694\ud569\ub2c8\ub2e4.\n\uc6b0\ub300\uc0ac\ud56d\n\u2022 Node.js \ubc0f TypeScript \uacbd\ud5d8\uc744 \uac00\uc9c4 \ubd84\uc744 \uc120\ud638\ud569\ub2c8\ub2e4.", "job_country": "KR", "industry": "IT, \ucee8\ud150\uce20", "company_id": 31582, "title_img": "https://static.wanted.co.kr/images/company/31582/em6pvsggh1sxqesm__1080_790.png", "due_time": null, "location": "\uacbd\uae30\ub3c4 \uc131\ub0a8\uc2dc \ubd84\ub2f9\uad6c \uc0bc\ud3c9\ub3d9 625 \ud310\uad50\uc138\ube10\ubca4\ucc98\ubc38\ub9ac1 \uc81c2\ub3d9 \uc81c 10\uce35 1002\ud638", "is_expert": true, "sub_categories": [".NET Developer", ".NET \uac1c\ubc1c\uc790", "Node.js Developer", "Node.js \uac1c\ubc1c\uc790", "Software Engineer", "Software Engineer", "\uc18c\ud504\ud2b8\uc6e8\uc5b4 \uc5d4\uc9c0\ub2c8\uc5b4"], "position": "\uac8c\uc784 \ud074\ub77c\uc774\uc5b8\ud2b8 \uac1c\ubc1c", "reward": 1000000, "jd": "METASPACE company\ub294 \ub124\uc774\ubc84\uc81c\ud2b8 \ucd9c\uc2e0\uc758 \uc778\ub825\ub4e4\uacfc \uc804\ubb38 \uac8c\uc784\uc5c5\uacc4 \uc778\ub825, \uadf8\ub9ac\uace0 \uba54\ud0c0\ubc84\uc2a4 \ud06c\ub9ac\uc5d0\uc774\ud130\ub85c \uad6c\uc131\ub418\uc5b4 \uc788\uc73c\uba70 \ud3c9\uade0\uc5f0\ub839 27\uc138\uc758 \uc80a\uc740 \ud68c\uc0ac\uc785\ub2c8\ub2e4. \n\n\ucd5c\uadfc \ub124\uc774\ubc84\uc81c\ud2b8\uc758 \ud22c\uc790\ub97c \ud1b5\ud574 \ud50c\ub7ab\ud3fc \ub0b4 \ucf58\ud150\uce20 \uacbd\uc7c1\ub825\uc744 \uc778\uc815\ubc1b\uc558\uc73c\uba70, \ud6c4\uc18d \ud22c\uc790\uc720\uce58\ub97c \ud1b5\ud574 \uc9c0\uc18d\uc801\uc778 \ud655\uc7a5\uc744 \ub3c4\ubaa8\ud558\uace0 \uc788\uc2b5\ub2c8\ub2e4. \n\n\uba54\ud0c0\uc2a4\ud398\uc774\uc2a4 \ucef4\ud37c\ub2c8\uc640 \ud568\uaed8 \ucc3d\uc758\ub825\uacfc \uc0c1\uc0c1\ub825\uc744 \uae30\ubc18\uc73c\ub85c \uc131\uc7a5\ud558\uba70, \uae00\ub85c\ubc8c \uc131\uacf5\uc744 \ud568\uaed8\ud558\uace0\uc790 \ud558\ub294 \uc778\uc7ac\ub97c \uae30\ub2e4\ub9bd\ub2c8\ub2e4.\n\n\n\uc8fc\uc694\uc5c5\ubb34\n\u2022 \uc81c\ud398\ud1a0 \uc2a4\ud06c\ub9bd\ud2b8(TypeScript)\ub97c \ud65c\uc6a9\ud574 \uc81c\ud398\ud1a0 \ub274\uc6d4\ub4dc \uac8c\uc784\uc744 \uac1c\ubc1c\ud569\ub2c8\ub2e4.\n\u2022 \uac1c\ubc1c\uc5d0 \ud544\uc694\ud55c \ub3c4\uad6c\ub97c \uac1c\ubc1c \ubc0f \uc720\uc9c0\ubcf4\uc218\ud569\ub2c8\ub2e4.\n\u2022 \uac1c\ubc1c\ud55c \uc18c\ud504\ud2b8\uc6e8\uc5b4\uc5d0 \ub300\ud55c \ubb38\uc11c\ub97c \uc791\uc131\ud569\ub2c8\ub2e4.\n\n\uc790\uaca9\uc694\uac74\n\u2022 1\ub144 \uc774\uc0c1\uc758 \uc720\ub2c8\ud2f0 \uac8c\uc784 \ud074\ub77c\uc774\uc5b8\ud2b8 \uacbd\ub825 \ubc0f \uadf8\uc5d0 \uc900\ud558\ub294 \uacbd\ud5d8\uc774 \uc788\uc73c\uc2e0 \ubd84\uc774 \ud544\uc694\ud569\ub2c8\ub2e4.\n\u2022 \uc720\ub2c8\ud2f0 \uc5d4\uc9c4\uc5d0 \ub300\ud55c \ub192\uc740 \uc774\ud574\ub3c4 \ubc0f \uc0ac\uc6a9 \uacbd\ud5d8\uc774 \uc788\uc73c\uc2e0 \ubd84\uc774 \ud544\uc694\ud569\ub2c8\ub2e4.\n\u2022 \uc608\uc0c1\uce58 \ubabb\ud55c \ub2e4\uc591\ud55c \ubb38\uc81c \uc0c1\ud669\uc5d0 \uc720\uc5f0\ud558\uac8c \ub300\ucc98 \uac00\ub2a5\ud558\uc2e0 \ubd84\uc774 \ud544\uc694\ud569\ub2c8\ub2e4.\n\uc6b0\ub300\uc0ac\ud56d\n\u2022 Node.js \ubc0f TypeScript \uacbd\ud5d8\uc744 \uac00\uc9c4 \ubd84\uc744 \uc120\ud638\ud569\ub2c8\ub2e4.\n\n\uc6b0\ub300\uc0ac\ud56d\n\u2022 \uae30\ud68d, \ub514\uc790\uc778, \ub9c8\ucf00\ud305 \ub4f1 \ub2e4\uc591\ud55c \uc9c1\uad70\uacfc \uc9c1\uc811\uc801\uc73c\ub85c \uc77c\ud574\ubcf8 \uacbd\ud5d8\uc774 \uc788\ub294 \ubd84\uc744 \uc120\ud638\ud569\ub2c8\ub2e4.\n\u2022 \uc790\ub8cc\uad6c\uc870, \uc6b4\uc601\uccb4\uc81c\uc640 \uac19\uc740 \ucef4\ud4e8\ud130 \uacf5\ud559\uc5d0 \ub300\ud55c \uc804\ubc18\uc801\uc778 \uc774\ub860\uc744 \uc798 \uc54c\uace0 \uacc4\uc2e0 \ubd84\uc744 \uc120\ud638\ud569\ub2c8\ub2e4.\n\u2022 \uc815\ud655\ud558\uace0 \uaf3c\uaf3c\ud55c \uc5c5\ubb34 \ucc98\ub9ac\uac00 \uac00\ub2a5\ud558\uc2e0 \ubd84\uc744 \uc120\ud638\ud569\ub2c8\ub2e4.\n\u2022 \uac8c\uc784 \ubfd0 \uc544\ub2c8\ub77c \ub2e4\uc591\ud55c \ubd84\uc57c\uc758 \ucf58\ud150\uce20\ub97c \uc990\uae30\ub294 \ubd84\uc744 \uc120\ud638\ud569\ub2c8\ub2e4.\n\u2022 \ud56d\uc0c1 \ub2a5\ub3d9\uc801\uc778 \uc790\uc138\ub97c \ubc14\ud0d5\uc73c\ub85c \uc5c5\ubb34\ub97c \uc9c4\ud589\ud558\ub294 \ubd84\uc744 \uc120\ud638\ud569\ub2c8\ub2e4.\n\n\ud61c\ud0dd \ubc0f \ubcf5\uc9c0\n\uc804\ud615\uc808\ucc28 \ubc0f \uae30\ud0c0 \uc0ac\ud56d \n\u2022 \uc811\uc218\uae30\uac04 :\u202f\uc0c1\uc2dc \n\u2022 \uc804\ud615\uc808\ucc28 : \ud3ec\ud2b8\ud3f4\ub9ac\uc624 \uc804\ud615 \uff1e \uba74\uc811 \uff1e \uc785\uc0ac \n\u2022 \ud3ec\ud2b8\ud3f4\ub9ac\uc624\ub294 pdf, \uae43\ud5c8\ube0c \ub9c1\ud06c, \uc6f9\uc0ac\uc774\ud2b8 \ub9c1\ud06c \ub4f1 \ud3b8\ud55c \ubc29\uc2dd\uc73c\ub85c \uc81c\ucd9c\ud574\uc8fc\uc2dc\uba74 \ub429\ub2c8\ub2e4.  \n\u2022 \uc804\ud615 \uc808\ucc28\ub294 \uc77c\uc815 \ubc0f \uc0c1\ud669\uc5d0 \ub530\ub77c \ubcc0\ub3d9\ub420 \uc218 \uc788\uc2b5\ub2c8\ub2e4. \n\u2022 \uc9c4\ud589 \uc77c\uc815\uc740 \ud655\uc815\ub418\ub294 \ub300\ub85c \uc9c0\uc6d0\uc790\ubd84\ub4e4\uc5d0\uac8c \uac1c\ubcc4 \uc548\ub0b4 \uc608\uc815\uc785\ub2c8\ub2e4. \n\u2022 \ubcf8 \ucc44\uc6a9\uc740 \ubaa8\uc9d1 \uae30\uac04 \ub0b4\uc5d0 \uc778\uc7ac \uc120\ubc1c \uc644\ub8cc \uc2dc \uacf5\uace0\uac00 \ub9c8\uac10\ub420 \uc218 \uc788\uc2b5\ub2c8\ub2e4. \n\n\n\uc548\ub0b4\uc0ac\ud56d \n\u2022 \uc9c0\uc6d0 \ub0b4\uc6a9 \uc911 \ud5c8\uc704 \uc0ac\uc2e4\uc774 \uc788\ub294 \uacbd\uc6b0\uc5d0\ub294 \ud569\uaca9\uc774 \ucde8\uc18c\ub420 \uc218 \uc788\uc2b5\ub2c8\ub2e4. \n\u2022 \ud574\uc678\uc5ec\ud589\uc5d0 \uacb0\uaca9 \uc0ac\uc720\uac00 \uc5c6\ub294 \ubd84\uc744 \ubaa8\uc9d1\ud558\uace0 \uc788\uc2b5\ub2c8\ub2e4.\n\u2022 \ubcf8 \uc804\ud615 \uc9c0\uc6d0 \uc644\ub8cc \uc2dc \uc0ac\uc6a9\ud55c \uc774\uba54\uc77c\ub85c \uc9c0\uc6d0\uc11c \uc81c\ucd9c \ud655\uc778 \uba54\uc77c\uc774 \ubc1c\uc1a1\ub418\uace0 \uc788\uc73c\uba70, \uc11c\ub958 \ud569\uaca9 \uc5ec\ubd80\ub294 \uacb0\uacfc\uc640 \uc0c1\uad00\uc5c6\uc774 \uac1c\uc778 \ubcc4 \uc548\ub0b4\ud574 \ub4dc\ub9ac\uace0 \uc788\uc2b5\ub2c8\ub2e4. \n\u2022 \uad6d\uac00\uc720\uacf5\uc790 \ubc0f \uc7a5\uc560\uc778 \ub4f1 \ucde8\uc5c5\ubcf4\ud638 \ub300\uc0c1\uc790\ub294 \uad00\uacc4\ubc95\ub839\uc5d0 \ub530\ub77c \uc6b0\ub300\ud569\ub2c8\ub2e4. \n\u2022 \uadfc\ubb34\uc9c0 : \uacbd\uae30\ub3c4 \uc131\ub0a8\uc2dc \ubd84\ub2f9\uad6c \uc0bc\ud3c9\ub3d9 625 \ud310\uad50\uc138\ube10\ubca4\ucc98\ubc38\ub9ac1 \uc81c2\ub3d9 \uc81c 10\uce35 1002\ud638\n\u202f \u203b \ucf54\ub85c\ub098 \uc5c5\ubb34 \uc0c1\ud669\uc5d0 \ub530\ub77c \uc6d0\uaca9\uadfc\ubb34\uac00 \uc9c4\ud589\ub420 \uc218 \uc788\uc73c\ub098, \uae30\ubcf8\uc801\uc73c\ub85c\ub294 \ucd9c\ud1f4\uadfc \uadfc\ubb34 \uc6d0\uce59\uc785\ub2c8\ub2e4.\n\n", "company_name": "\uba54\ud0c0\uc2a4\ud398\uc774\uc2a4", "lang": "ko", "gps_x": "127.101243786453", "gps_y": "37.4015384523489", "tags": ["#\uc6d0\uaca9\uadfc\ubb34", "#IT, \ucee8\ud150\uce20"], "tools": ["Git", "Github", "C#", "JavaScript", "Node.js", "TypeScript", "Unity3D"]}