{"status": "active", "title_thumb_img": "https://static.wanted.co.kr/images/company/31632/fztuwbtsydpj3n5e__400_400.png", "is_newbie": false, "currency": "KRW", "logo_thumb_img": "https://static.wanted.co.kr/images/wdes/0_5.e0784705.jpg", "logo_img": "https://static.wanted.co.kr/images/wdes/0_4.e0784705.jpg", "address": {"country": "\ud55c\uad6d", "id": 38129, "location": "\uc11c\uc6b8"}, "confirm_time": "2022-11-17T17:44:51", "id": 137043, "category": "IT", "main_tasks": "\u2022 \uacf5\uac04 \uc815\ubcf4 \uc6f9 \uc2dc\uc2a4\ud15c \uac1c\ubc1c\n\u2022 \ud574\uc591, \uae30\uc0c1 \uad00\ub828 \ud504\ub85c\uc81d\ud2b8 \ubc0f R & D \uac1c\ubc1c", "requirements": "\u2022 \uc6f9 \uac1c\ubc1c \uacbd\ub825 5\ub144 \uc774\uc0c1 \ub610\ub294 \uadf8\uc5d0 \uc900\ud558\ub294 \uc790\n\u2022 java, spring \ud504\ub85c\uc81d\ud2b8 \uac1c\ubc1c \uacbd\ud5d8\uc790\n\u2022 DB \uc124\uacc4 \ubc0f SQL \uac1c\ubc1c \uac00\ub2a5\uc790", "job_country": "KR", "industry": "IT, \ucee8\ud150\uce20", "company_id": 31632, "title_img": "https://static.wanted.co.kr/images/company/31632/fztuwbtsydpj3n5e__1080_790.png", "due_time": null, "location": "\uc11c\uc6b8\ud2b9\ubcc4\uc2dc \uad6c\ub85c\uad6c \uacbd\uc778\ub85c 53\uae38 90 STX-W Tower 1501\ud638~1504\ud638", "is_expert": true, "sub_categories": ["Java Developer", "\uc790\ubc14 \uac1c\ubc1c\uc790", "Back-end Engineer", "\uc11c\ubc84 \uac1c\ubc1c\uc790", "Web Developer", "\uc6f9 \uac1c\ubc1c\uc790"], "position": "GIS \uc6f9 \uac1c\ubc1c", "reward": 1000000, "jd": "\ud55c\uad6d\ud574\uc591\uae30\uc0c1\uae30\uc220\uc740\n\uae30\uc0c1\uccad \uad00\ub828 \ud504\ub85c\uc81d\ud2b8\uc640 \uc815\ubd80 R&D\ub97c \uc8fc\ub85c \ud558\uace0 \uc788\uc2b5\ub2c8\ub2e4.\n\uc6f9 \uac1c\ubc1c \ud504\ub85c\uc81d\ud2b8 \uc804\uccb4\ub97c \ub9ac\ub529\ud560 \uac1c\ubc1c\uc790\ub97c \ubaa8\uc9d1 \ud569\ub2c8\ub2e4.\n\n\n\uc8fc\uc694\uc5c5\ubb34\n\u2022 \uacf5\uac04 \uc815\ubcf4 \uc6f9 \uc2dc\uc2a4\ud15c \uac1c\ubc1c\n\u2022 \ud574\uc591, \uae30\uc0c1 \uad00\ub828 \ud504\ub85c\uc81d\ud2b8 \ubc0f R & D \uac1c\ubc1c\n\n\uc790\uaca9\uc694\uac74\n\u2022 \uc6f9 \uac1c\ubc1c \uacbd\ub825 5\ub144 \uc774\uc0c1 \ub610\ub294 \uadf8\uc5d0 \uc900\ud558\ub294 \uc790\n\u2022 java, spring \ud504\ub85c\uc81d\ud2b8 \uac1c\ubc1c \uacbd\ud5d8\uc790\n\u2022 DB \uc124\uacc4 \ubc0f SQL \uac1c\ubc1c \uac00\ub2a5\uc790\n\n\uc6b0\ub300\uc0ac\ud56d\n\u2022 geoserver, openlayer, postgis, qgis, cesium \uc911 \ud558\ub098\ub77c\ub3c4 \uac1c\ubc1c \uacbd\ud5d8\uc774 \uc788\uc73c\uc2e0 \ubd84\n\u2022 \uacf5\uac04 \uc815\ubcf4 \ub610\ub294 \ud574\uc591, \uae30\uc0c1 \uad00\ub828 \ud504\ub85c\uc81d\ud2b8 \uacbd\ud5d8\uc774 \uc788\uc73c\uc2e0 \ubd84  \n\u2022 msa, kafka, elastic search, kubernetes \ub4f1 \uc0ac\uc6a9 \uacbd\ud5d8\uc774 \uc788\uc73c\uc2e0 \ubd84\n\n\ud61c\ud0dd \ubc0f \ubcf5\uc9c0\n\u2022 \uc810\uc2ec \uc2dd\ub300 \uc81c\uacf5, \uac04\uc2dd \uc81c\uacf5\n\u2022 \uc8fc 5\uc77c, 4\ub300 \ubcf4\ud5d8, \uc778\uc13c\ud2f0\ube0c\uc81c, \uc7a5\uae30 \uadfc\uc18d\uc790 \ud3ec\uc0c1 \ub4f1\n\n", "company_name": "\ud55c\uad6d\ud574\uc591\uae30\uc0c1\uae30\uc220", "lang": "ko", "gps_x": "126.875175609908", "gps_y": "37.5047173676191", "tags": ["#\uc5f0\ubd09\uc5c5\uacc4\ud3c9\uade0\uc774\uc0c1", "#\ud1f4\uc0ac\uc7285%\uc774\ud558", "#50\uba85\uc774\ud558", "#\uc124\ub9bd10\ub144\uc774\uc0c1", "#\uac04\uc2dd", "#IT, \ucee8\ud150\uce20"], "tools": ["Pytorch", "Tensorflow", "Python"]}